avenida/__init__.py
avenida/main.py
avenida-0.1.0.dist-info/WHEEL
avenida-0.1.0.dist-info/METADATA
avenida-0.1.0.dist-info/RECORD
